Metadata-Version: 2.1
Name: soda-core-impala
Version: 3.5.6
License-File: LICENSE
Requires-Dist: soda-core==3.5.6
Requires-Dist: impyla==0.19.0
